recmd/__init__.py
recmd/command.py
recmd/exceptions.py
recmd/map_result.py
recmd/patcher.py
recmd/shell.py
recmd/shell_patch.py
recmd/stream.py
recmd/template.py
recmd/executor/abc.py
recmd/executor/anyio.py
recmd/executor/subprocess.py
recmd-0.2.0.dist-info/licenses/LICENSE
recmd-0.2.0.dist-info/METADATA
recmd-0.2.0.dist-info/WHEEL
recmd-0.2.0.dist-info/top_level.txt
recmd-0.2.0.dist-info/RECORD
