Metadata-Version: 2.4
Name: recmd
Version: 0.2.0
Summary: Inspired by zx command constructor
Author-email: Ivan Vozhakov <gou177@bk.ru>
License: MIT License
Project-URL: Homepage, https://github.com/gou177/recmd
Keywords: command,shell,subprocess
Classifier: License :: OSI Approved :: MIT License
Classifier: Programming Language :: Python
Classifier: Programming Language :: Python :: 3
Requires-Python: >=3.12
License-File: LICENSE
Provides-Extra: async
Requires-Dist: anyio; extra == "async"
Provides-Extra: dev
Requires-Dist: anyio; extra == "dev"
Requires-Dist: pytest; extra == "dev"
Requires-Dist: trio; extra == "dev"
Dynamic: license-file
